lwksprefs.py
lwksprefs-0.1.dist-info/METADATA
lwksprefs-0.1.dist-info/RECORD
lwksprefs-0.1.dist-info/WHEEL
lwksprefs-0.1.dist-info/top_level.txt
