Metadata-Version: 2.1
Name: lwksprefs
Version: 0.1
Summary: Lightworks NLE preferences reader
Home-page: https://gitlab.com/marcinjn/lwksprefs
Author: Marcin Nowak
Author-email: marcin.j.nowak@gmail.com
License: UNKNOWN
Keywords: lwks lightworks parser
Platform: UNKNOWN
Classifier: Development Status :: 3 - Alpha
Classifier: Intended Audience :: Developers
Classifier: Programming Language :: Python :: 3.7
Classifier: License :: OSI Approved :: GNU General Public License v3 (GPLv3)
Classifier: Operating System :: POSIX :: Linux
Classifier: Topic :: Software Development :: Libraries
Classifier: Topic :: Software Development :: Libraries :: Python Modules
